abedwomar-0.1.0.dist-info/licenses/LICENSE
demo_greeter_pkg/__init__.py
demo_greeter_pkg/greet.py
demo_greeter_pkg/venv/Lib/site-packages/pip/__init__.py
demo_greeter_pkg/venv/Lib/site-packages/pip/__main__.py
demo_greeter_pkg/venv/Lib/site-packages/pip/__pip-runner__.py
demo_greeter_pkg/venv/Lib/site-packages/pip/py.typed
demo_greeter_pkg/venv/Lib/site-packages/pip/_internal/__init__.py
demo_greeter_pkg/venv/Lib/site-packages/pip/_internal/build_env.py
demo_greeter_pkg/venv/Lib/site-packages/pip/_internal/cache.py
demo_greeter_pkg/venv/Lib/site-packages/pip/_internal/configuration.py
demo_greeter_pkg/venv/Lib/site-packages/pip/_internal/exceptions.py
demo_greeter_pkg/venv/Lib/site-packages/pip/_internal/main.py
demo_greeter_pkg/venv/Lib/site-packages/pip/_internal/pyproject.py
demo_greeter_pkg/venv/Lib/site-packages/pip/_internal/self_outdated_check.py
demo_greeter_pkg/venv/Lib/site-packages/pip/_internal/wheel_builder.py
demo_greeter_pkg/venv/Lib/site-packages/pip/_internal/cli/__init__.py
demo_greeter_pkg/venv/Lib/site-packages/pip/_internal/cli/autocompletion.py
demo_greeter_pkg/venv/Lib/site-packages/pip/_internal/cli/base_command.py
demo_greeter_pkg/venv/Lib/site-packages/pip/_internal/cli/cmdoptions.py
demo_greeter_pkg/venv/Lib/site-packages/pip/_internal/cli/command_context.py
demo_greeter_pkg/venv/Lib/site-packages/pip/_internal/cli/index_command.py
demo_greeter_pkg/venv/Lib/site-packages/pip/_internal/cli/main.py
demo_greeter_pkg/venv/Lib/site-packages/pip/_internal/cli/main_parser.py
demo_greeter_pkg/venv/Lib/site-packages/pip/_internal/cli/parser.py
demo_greeter_pkg/venv/Lib/site-packages/pip/_internal/cli/progress_bars.py
demo_greeter_pkg/venv/Lib/site-packages/pip/_internal/cli/req_command.py
demo_greeter_pkg/venv/Lib/site-packages/pip/_internal/cli/spinners.py
demo_greeter_pkg/venv/Lib/site-packages/pip/_internal/cli/status_codes.py
demo_greeter_pkg/venv/Lib/site-packages/pip/_internal/commands/__init__.py
demo_greeter_pkg/venv/Lib/site-packages/pip/_internal/commands/cache.py
abedwomar-0.1.0.dist-info/METADATA
abedwomar-0.1.0.dist-info/WHEEL
abedwomar-0.1.0.dist-info/entry_points.txt
abedwomar-0.1.0.dist-info/top_level.txt
abedwomar-0.1.0.dist-info/RECORD
